cast/.DS_Store
cast/.streamlit/config.toml
cast/__init__.py
cast/app.py
cast/assets/cast.png
cast/assets/comparisons.md
cast/assets/conditionals.md
cast/assets/joins.md
cast/assets/logo.png
cast/assets/numerical.md
cast/assets/types.md
cast/components/__init__.py
cast/components/bi_tool.py
cast/components/extract.py
cast/components/graph.py
cast/main.py
cast/utils/__init__.py
cast/utils/config.py
cast/utils/data_profiler.py
cast/utils/documentation.py
cast/utils/files.py
cast/utils/uploader.py
exakt_cast-0.0.8.dist-info/METADATA
exakt_cast-0.0.8.dist-info/WHEEL
exakt_cast-0.0.8.dist-info/entry_points.txt
exakt_cast-0.0.8.dist-info/licenses/LICENSE
exakt_cast-0.0.8.dist-info/RECORD
