Metadata-Version: 2.1
Name: exakt-cast
Version: 0.0.8
Summary: Cast is an app that allows you to wrangle your data locally using DuckDB
Author-Email: Kobus Rust <kobus@exakt.ai>
Classifier: Intended Audience :: Science/Research
Classifier: Operating System :: OS Independent
Classifier: Programming Language :: Python :: 3
Classifier: Programming Language :: Python
Classifier: Topic :: Scientific/Engineering
Classifier: Development Status :: 4 - Beta
Classifier: License :: OSI Approved :: GNU General Public License v3 (GPLv3)
Classifier: Programming Language :: Python :: 3 :: Only
Classifier: Programming Language :: Python :: 3.9
Classifier: Programming Language :: Python :: 3.10
Classifier: Programming Language :: Python :: 3.11
Classifier: Programming Language :: Python :: 3.12
Project-URL: Homepage, https://www.exakt.ai/
Project-URL: Documentation, https://cast.exakt.ai/
Project-URL: Repository, https://github.com/ExaktOSS/cast
Requires-Python: <3.13,>=3.9
Requires-Dist: duckdb>=1.1.0
Requires-Dist: streamlit>=1.41.1
Requires-Dist: pandas>=2.2.3
Requires-Dist: polars>=1.19.0
Requires-Dist: pyarrow>=17.0.0
Requires-Dist: s3fs>=2023.9.0
Requires-Dist: scipy>=1.11.3
Requires-Dist: pygwalker>=0.4.9.9
Requires-Dist: streamlit-monaco==0.1.3
Requires-Dist: plotly>=5.24.1
